setup.py
frame/__init__.py
frame/_app.py
frame/_config.py
frame/_logger.py
frame/_routes.py
frame/caching.py
frame/controller.py
frame/dispatchers.py
frame/dotdict.py
frame/driverdatabase.py
frame/driverinterface.py
frame/errors.py
frame/header.py
frame/headersdict.py
frame/postprocessors.py
frame/preprocessors.py
frame/request.py
frame/response.py
frame/staticdispatcher.py
frame/staticgenerator.py
frame/threaddata.py
frame/toolset.py
frame/treedict.py
frame/util.py
frame.egg-info/PKG-INFO
frame.egg-info/SOURCES.txt
frame.egg-info/dependency_links.txt
frame.egg-info/entry_points.txt
frame.egg-info/requires.txt
frame.egg-info/top_level.txt
frame/extensions/__init__.py
frame/extensions/jade.py
frame/extensions/sessions.py
frame/extensions/templates.py
frame/server/__init__.py
frame/server/headers.py
frame/server/http.py
frame/server/modulemonitor.py
frame/server/worker.py
frame/static/css/forms.css
frame/static/css/global.css
frame/static/js/form.js
frame/static/js/global.js
frame/static/js/jquery.js
frame/static/js/require.js
frame/templates/traceback.html
frame/templates/__errors/jinja2/401.html
frame/templates/__errors/jinja2/404.html
frame/templates/__errors/jinja2/500.html
frame/templates/__errors/jinja2/generic.html
frame/templates/__errors/jinja2/template.html
frame/templates/forms/close_item_group.html
frame/templates/forms/macros.html
frame/templates/forms/open_item_group.html
frame/templates/forms/wrapper.html
frame/templates/forms/elements/email.html
frame/templates/forms/elements/generic_element.html
frame/templates/forms/elements/password.html
frame/templates/forms/elements/radio.html
frame/templates/forms/elements/select.html
frame/templates/forms/elements/submit.html
frame/templates/forms/includes/arguments.html
frame/templates/forms/includes/default.html
frame/templates/includes/footer.html
frame/templates/includes/header.html
frame/templates/js/make_form_validation.js
frame/templates/macros/pagination.html
frame/testsuite/_app.py
frame/testsuite/_routes.py
frame/testsuite/dotdict.py
frame/testsuite/postprocessors.py
frame/testsuite/preprocessors.py
frame/testsuite/request.py
frame/testsuite/response.py
