Metadata-Version: 1.0
Name: frame
Version: 0.3.1
Summary: A very simple, lightweight MVC-based web framework.
Home-page: UNKNOWN
Author: Tim Radke
Author-email: countach74@gmail.com
License: GNU
Keywords: web framework mvc
Platform: UNKNOWN
